tympy/__init__.py
tympy/tympy.py
tympy-0.1.1.dist-info/LICENSE
tympy-0.1.1.dist-info/METADATA
tympy-0.1.1.dist-info/WHEEL
tympy-0.1.1.dist-info/top_level.txt
tympy-0.1.1.dist-info/RECORD
