Metadata-Version: 2.1
Name: tympy
Version: 0.1.1
Summary: A Python library for observing output and execution times of scripts.
Home-page: https://github.com/inidal/tympy
Author: Nidal Iguer
Author-email: Nidal Iguer <hello@inidal.dev>
Project-URL: Homepage, https://github.com/inidal/tympy
Project-URL: Issues, https://github.com/inidal/tympy/issues
Classifier: Programming Language :: Python :: 3
Classifier: License :: OSI Approved :: MIT License
Classifier: Operating System :: OS Independent
Requires-Python: >=3.6
License-File: LICENSE
